Workbook

Sheet Side by Side
A1: UK vs Hong Kong - Side-by-side monthly cost comparison
A2: Purpose: compare Hong Kong and UK assumptions category by category. Housing now comes from the Housing Mechanics sheet, which splits common property obligations, rent income, mortgage principal and one-off agency fees. Use the validation notes to decide which rows need transaction-level checking.
A4: Hong Kong check | B4: £/mo | C4: UK check | D4: £/mo | E4: Delta / note | F4: Value
A5: HK side-by-side category total | B5: =SUM(B13:B33) | C5: UK settled category total | D5: =SUM(C13:C33) | E5: UK minus HK | F5: =D5-B5
A6: HK trend benchmark after Cecil offset | B6: =Inputs!$B$14/Inputs!$B$4-Inputs!$B$18 | C6: UK corrected settled cash burn | D6: =Inputs!$B$45 | E6: UK minus HK benchmark | F6: =D6-B6
A7: UK search-phase input | B7: =Inputs!$B$50 | C7: UK search-phase column H total | D7: =H35 | E7: Column H minus B50 | F7: =D7-B7
A12: Category | B12: Hong Kong £/mo | C12: UK £/mo | D12: UK minus HK £/mo | E12: Higher side | F12: Validation note | G12: Opt (UK, during search) | H12: UK search-phase GBP/mo | I12: Confidence | J12: Source row
A13: Housing (net property cash) | B13: ='Housing Mechanics'!B31 | C13: ='Housing Mechanics'!B32 | D13: =C13-B13 | E13: =IF(ABS(D13)<25,"Similar",IF(D13>0,"UK higher","HK higher")) | F13: Housing Mechanics: net property cash, one-off agency fee excluded. | G13: Non-optional | H13: =C13 | I13: High | J13: Housing Mechanics key outputs
A14: Tax | B14: ='Category Map'!D5/Inputs!$B$4 | C14: ='Category Map'!E5 | D14: =C14-B14 | E14: =IF(ABS(D14)<25,"Similar",IF(D14>0,"UK higher","HK higher")) | F14: Income-tax handled in income scenarios. | G14: Non-optional | H14: =C14 | I14: High | J14: Category Map row 5
A15: Travel | B15: ='Category Map'!D6/Inputs!$B$4 | C15: ='Category Map'!E6 | D15: =C15-B15 | E15: =IF(ABS(D15)<25,"Similar",IF(D15>0,"UK higher","HK higher")) | F15: Not in corrected UK burn B45; review separately if needed. | G15: Discretionary | H15: =0 | I15: Low | J15: Category Map row 6
A16: Tuition | B16: ='Category Map'!D7/Inputs!$B$4 | C16: ='Category Map'!E7 | D16: =C16-B16 | E16: =IF(ABS(D16)<25,"Similar",IF(D16>0,"UK higher","HK higher")) | F16: UK state school removes school fees. | G16: Non-optional | H16: =C16 | I16: High | J16: Category Map row 7
A17: Dining out | B17: ='Category Map'!D8/Inputs!$B$4 | C17: ='Category Map'!E8 | D17: =C17-B17 | E17: =IF(ABS(D17)<25,"Similar",IF(D17>0,"UK higher","HK higher")) | F17: Discretionary during search: keep 40%. | G17: Discretionary | H17: =C17*0.4 | I17: Medium | J17: Category Map row 8
A18: Groceries | B18: ='Category Map'!D9/Inputs!$B$4 | C18: ='Category Map'!E9 | D18: =C18-B18 | E18: =IF(ABS(D18)<25,"Similar",IF(D18>0,"UK higher","HK higher")) | F18: Non-optional food line. | G18: Non-optional | H18: =C18 | I18: Medium | J18: Category Map row 9
A19: Bills / household utilities | B19: ='Category Map'!D10/Inputs!$B$4 | C19: ='Category Map'!E10 | D19: =C19-B19 | E19: =IF(ABS(D19)<25,"Similar",IF(D19>0,"UK higher","HK higher")) | F19: HK helper split out; this is utilities/household bills only. | G19: Non-optional | H19: =C19 | I19: Medium | J19: Category Map row 10
A20: Health / gym | B20: ='Category Map'!D11/Inputs!$B$4 | C20: ='Category Map'!E11 | D20: =C20-B20 | E20: =IF(ABS(D20)<25,"Similar",IF(D20>0,"UK higher","HK higher")) | F20: Discretionary during search: cut to zero. | G20: Discretionary | H20: =0 | I20: Medium | J20: Category Map row 11
A21: Leisure | B21: ='Category Map'!D12/Inputs!$B$4 | C21: ='Category Map'!E12 | D21: =C21-B21 | E21: =IF(ABS(D21)<25,"Similar",IF(D21>0,"UK higher","HK higher")) | F21: Discretionary during search: keep 30%. | G21: Discretionary | H21: =C21*0.3 | I21: Medium | J21: Category Map row 12
A22: Medical | B22: ='Category Map'!D13/Inputs!$B$4 | C22: ='Category Map'!E13 | D22: =C22-B22 | E22: =IF(ABS(D22)<25,"Similar",IF(D22>0,"UK higher","HK higher")) | F22: NHS line, currently zero. | G22: Non-optional | H22: =C22 | I22: Medium | J22: Category Map row 13
A23: Transport (TfL) | B23: ='Category Map'!D14/Inputs!$B$4 | C23: ='Category Map'!E14 | D23: =C23-B23 | E23: =IF(ABS(D23)<25,"Similar",IF(D23>0,"UK higher","HK higher")) | F23: TfL / rail line, separate from car. | G23: Non-optional | H23: =C23 | I23: Medium | J23: Category Map row 14
A24: Car | B24: ='Category Map'!D15/Inputs!$B$4 | C24: ='Category Map'!E15 | D24: =C24-B24 | E24: =IF(ABS(D24)<25,"Similar",IF(D24>0,"UK higher","HK higher")) | F24: Settled-life car running cost; deferred during search. | G24: Discretionary | H24: =Inputs!$B$47 | I24: Medium | J24: Category Map row 15
A25: Shopping / clothing | B25: ='Category Map'!D16/Inputs!$B$4 | C25: ='Category Map'!E16 | D25: =C25-B25 | E25: =IF(ABS(D25)<25,"Similar",IF(D25>0,"UK higher","HK higher")) | F25: Discretionary during search: keep 40%. | G25: Discretionary | H25: =C25*0.4 | I25: Low | J25: Category Map row 16
A26: Beauty / personal care | B26: ='Category Map'!D17/Inputs!$B$4 | C26: ='Category Map'!E17 | D26: =C26-B26 | E26: =IF(ABS(D26)<25,"Similar",IF(D26>0,"UK higher","HK higher")) | F26: Personal care retained during search. | G26: Non-optional | H26: =C26 | I26: Medium | J26: Category Map row 17
A27: Savings & Investments | B27: ='Category Map'!D18/Inputs!$B$4 | C27: ='Category Map'!E18 | D27: =C27-B27 | E27: =IF(ABS(D27)<25,"Similar",IF(D27>0,"UK higher","HK higher")) | F27: Excluded from floor. | G27: Discretionary | H27: =0 | I27: High | J27: Category Map row 18
A28: Financial / work subs | B28: ='Category Map'!D19/Inputs!$B$4 | C28: ='Category Map'!E19 | D28: =C28-B28 | E28: =IF(ABS(D28)<25,"Similar",IF(D28>0,"UK higher","HK higher")) | F28: Work AI subscriptions retained. | G28: Non-optional | H28: =C28 | I28: Medium | J28: Category Map row 19
A29: Sophia essentials | B29: ='Category Map'!D20/Inputs!$B$4 | C29: ='Category Map'!E20 | D29: =C29-B29 | E29: =IF(ABS(D29)<25,"Similar",IF(D29>0,"UK higher","HK higher")) | F29: Provisional 50% split of Sophia line until itemised. | G29: Non-optional | H29: =C29 | I29: Low | J29: Category Map row 20
A30: Sophia clubs/activities | B30: ='Category Map'!D21/Inputs!$B$4 | C30: ='Category Map'!E21 | D30: =C30-B30 | E30: =IF(ABS(D30)<25,"Similar",IF(D30>0,"UK higher","HK higher")) | F30: Discretionary during search: halve. | G30: Discretionary | H30: =C30*0.5 | I30: Low | J30: Category Map row 21
A31: Buffer / lumpy | B31: ='Category Map'!D22/Inputs!$B$4 | C31: ='Category Map'!E22 | D31: =C31-B31 | E31: =IF(ABS(D31)<25,"Similar",IF(D31>0,"UK higher","HK higher")) | F31: Discretionary during search: keep 50%. | G31: Discretionary | H31: =C31*0.5 | I31: Low | J31: Category Map row 22
A32: Domestic help / cleaner | B32: ='Category Map'!D23/Inputs!$B$4 | C32: ='Category Map'!E23 | D32: =C32-B32 | E32: =IF(ABS(D32)<25,"Similar",IF(D32>0,"UK higher","HK higher")) | F32: Settled cleaner B26; search-phase cleaning B49. | G32: Discretionary | H32: =Inputs!$B$49 | I32: Low | J32: Category Map row 23
A33: Babysitting / childcare cover | B33: ='Category Map'!D24/Inputs!$B$4 | C33: ='Category Map'!E24 | D33: =C33-B33 | E33: =IF(ABS(D33)<25,"Similar",IF(D33>0,"UK higher","HK higher")) | F33: Settled babysitting B42; search-phase babysitting B48. | G33: Discretionary | H33: =Inputs!$B$48 | I33: Low | J33: Category Map row 24
A34: UK settled total (all lines) | C34: =SUM(C13:C33) | D34: =C34-Inputs!$B$45 | F34: Column C sum versus Inputs B45 corrected cash burn | H34: =Inputs!$B$45 | J34: Inputs B45
A35: UK SEARCH-PHASE non-optional floor total | C35: =Inputs!$B$50 | D35: =H35-C35 | F35: =IF(ABS(H35-Inputs!$B$50)<=25,"Ties to Inputs B50","Diverges from B50 because Column H applies discretionary cuts to dining, leisure, shopping, buffer and Sophia activities; Inputs B50 only swaps cleaner, babysitting and car on top of base burn.") | H35: =SUM(H13:H33) | J35: Column H vs Inputs B50
A36: Malvern cash burn context | C36: 1593 | F36: Echo from uk-move-financial-model section 9, as requested | J36: Context only
A37: Search tie note | F37: If Column H is materially below B50, the workbook is exposing two different search assumptions: true discretionary cuts versus B50 lean burn. Decide which one should govern the decision model.
A39: How to read this sheet
A40: 1 | B40: Column C is settled-life UK cost. It should tie approximately to Inputs B45.
A41: 2 | B41: Column G classifies each UK line during job search using the Non-optional / Discretionary convention from budget.md.
A42: 3 | B42: Column H is the search-phase floor after discretionary cuts. It is intentionally checked against Inputs B50.
A43: 4 | B43: If Column H diverges from B50, the note above explains the modelling difference rather than hiding it.

Sheet Housing Mechanics
A1: Housing mechanics - split owner costs, debt service, rent and one-offs
A2: Housing cannot be compared as HK$29k versus a UK housing line. Both properties are owned in both scenarios, and several costs are paid regardless of location. This sheet separates common owner obligations from the rent and tax flows that actually change when Julian is in Hong Kong versus London.
A5: Property | B5: Component | C5: HKD/mo | D5: GBP/mo | E5: Common both? | F5: HK-stay | G5: London | H5: Notes
A6: DB flat | B6: Mortgage total | C6: ='Inputs'!B32 | D6: =C6/'Inputs'!$B$4 | E6: Yes | F6: Home cost | G6: Let cost | H6: Debt service paid either way
A7: DB flat | B7: of which interest | C7: ='Inputs'!B33 | D7: =C7/'Inputs'!$B$4 | E7: Yes | F7: Included above | G7: Included above | H7: Consumption cost, but paid either way while flat is held
A8: DB flat | B8: of which principal | C8: ='Inputs'!B34 | D8: =C8/'Inputs'!$B$4 | E8: Yes | F8: Included above | G8: Included above | H8: Equity repayment, not consumption
A9: DB flat | B9: Management fee | C9: ='Inputs'!B35 | D9: =C9/'Inputs'!$B$4 | E9: Yes | F9: Home cost | G9: Let cost | H9: Paid while flat is held
A10: DB flat | B10: Rates | C10: ='Inputs'!B36 | D10: =C10/'Inputs'!$B$4 | E10: Yes | F10: Home cost | G10: Let cost | H10: Paid while flat is held
A11: DB flat | B11: HK property tax when let | C11: ='Inputs'!B37 | D11: =C11/'Inputs'!$B$4 | E11: No | F11: No | G11: Yes | H11: Only arises when DB flat is rented out
A12: DB flat | B12: Rent when let | C12: ='Inputs'!B30 | D12: =C12/'Inputs'!$B$4 | E12: No | F12: No | G12: Income | H12: Anticipated HK$22,000/mo rent
A13: DB flat | B13: Letting agency fee | C13: ='Inputs'!B31 | D13: =C13/'Inputs'!$B$4 | E13: No | F13: No | G13: One-off | H13: One-off 50% of one month rent, excluded from monthly central
A14: Cecil Road | B14: Mortgage | C14: ='Inputs'!B38*'Inputs'!$B$4 | D14: ='Inputs'!B38 | E14: Yes | F14: Let cost | G14: Home cost | H14: Interest-only mortgage paid either way
A15: Cecil Road | B15: Insurance | C15: ='Inputs'!B39*'Inputs'!$B$4 | D15: ='Inputs'!B39 | E15: Yes | F15: Let cost | G15: Home cost | H15: Buildings insurance paid either way
A16: Cecil Road | B16: Take-home rent before owner costs | C16: ='Inputs'!B40*'Inputs'!$B$4 | D16: ='Inputs'!B40 | E16: No | F16: Income | G16: No | H16: Rent after management and rent protection
A17: Cecil Road | B17: UK rental tax | C17: ='Inputs'!B41*'Inputs'!$B$4 | D17: ='Inputs'!B41 | E17: No | F17: Yes | G17: No | H17: Only arises when Cecil is rented out
A21: Monthly comparison views
A22: View | B22: HK-stay £/mo | C22: London £/mo | D22: London minus HK £/mo | E22: Read | F22: Included in side-by-side? | G22: Formula basis | H22: Notes
A23: Pure location rent/tax flows, common owner costs excluded | B23: =-('Inputs'!B40-'Inputs'!B41) | C23: =-('Inputs'!B30-'Inputs'!B37)/'Inputs'!$B$4 | D23: =C23-B23 | E23: =IF(D23>0,"London worse",IF(D23<0,"London better","No difference")) | F23: Diagnostic | G23: Only rent and tax flows that differ by location | H23: Shows the same delta after cancelling common obligations.
A24: Full monthly property cash cost, excluding one-off agency fee | B24: =('Inputs'!B32+'Inputs'!B35+'Inputs'!B36)/'Inputs'!$B$4-'Inputs'!B18 | C24: ='Inputs'!B38+'Inputs'!B39+('Inputs'!B32+'Inputs'!B35+'Inputs'!B36+'Inputs'!B37-'Inputs'!B30)/'Inputs'!$B$4 | D24: =C24-B24 | E24: =IF(D24>0,"London worse",IF(D24<0,"London better","No difference")) | F24: Yes | G24: All monthly cash outflows and rent offsets, one-off agency excluded | H24: This replaces the misleading HK £2,900 versus UK £1,289 housing row.
A25: Net-worth basis, DB principal added back both sides | B25: =B24-'Inputs'!B21 | C25: =C24-'Inputs'!B21 | D25: =C25-B25 | E25: =IF(D25>0,"London worse",IF(D25<0,"London better","No difference")) | F25: Diagnostic | G25: Cash view less DB principal/equity component | H25: Same delta because DB principal is common.
A26: First-year average if agency fee spread over 12 months | B26: =B24 | C26: =C24+'Inputs'!B31/'Inputs'!$B$4/12 | D26: =C26-B26 | E26: =IF(D26>0,"London worse",IF(D26<0,"London better","No difference")) | F26: Sensitivity | G26: One-off fee annualised for first-year cash planning | H26: Do not treat as permanent monthly burn.
A30: Key outputs
A31: HK-stay monthly housing cost for side-by-side | B31: =B24 | C31: Used as Side by Side HK housing row
A32: London monthly housing cost for side-by-side | B32: =C24 | C32: Used as Side by Side UK housing row
A33: Ongoing monthly London disadvantage | B33: =D24 | C33: About £59/mo before one-off agency fee
A34: One-off DB letting agency fee | B34: ='Inputs'!B31/'Inputs'!$B$4 | C34: About £1,100 one-off
A35: First-year agency equivalent | B35: ='Inputs'!B31/'Inputs'!$B$4/12 | C35: About £92/mo for year one only

Sheet Inputs
A1: UK vs HK Income Floor Reconciliation
A2: Editable assumptions. Yellow cells are primary inputs; blue cells are source-derived constants.
A3: Input | B3: Value | C3: Notes | D3: Source
A4: FX HKD per GBP | B4: 10 | C4: Model convention used across relocation files. | D4: finance/uk-vs-hk-cost-comparison.md
A5: HK 100k role gross monthly HKD | B5: 100000 | C5: Lower-paid HK role test raised by Julian. | D5: finance/uk-move-financial-model.md §8
A6: HK 100k role effective tax rate | B6: 0.15 | C6: Rounded salaries-tax assumption used in current model. | D6: finance/uk-move-financial-model.md §8
A7: HK senior role gross monthly HKD | B7: 125000 | C7: Mid senior role sensitivity. | D7: Scenario input
A8: HK senior role effective tax rate | B8: 0.15 | C8: Rounded salaries-tax assumption. | D8: Scenario input
A9: UK strong role gross annual GBP | B9: 120000 | C9: UK strong-but-not-150k scenario. | D9: career/uk-150k-feasibility-jh-clarifications-2026-07-09.md
A10: UK strong role net annual GBP | B10: 76158 | C10: PAYE estimate, no pension salary sacrifice. | D10: career/uk-150k-feasibility-jh-clarifications-2026-07-09.md
A11: UK floor role gross annual GBP | B11: 77500 | C11: Cash-flow break-even gross floor. | D11: career/uk-150k-feasibility-report.md
A12: UK floor role net annual GBP | B12: 55508 | C12: PAYE estimate, no pension salary sacrifice. | D12: career/uk-150k-feasibility-jh-clarifications-2026-07-09.md
A13: HK actual 12-mo mean burn HKD | B13: 92196 | C13: Actual monthly burn, Jul 2025-Jun 2026. | D13: finance/uk-move-financial-model.md §1
A14: HK actual 6-mo trend burn HKD | B14: 83940 | C14: Recent monthly burn, Jan-Jun 2026. | D14: finance/uk-move-financial-model.md §1
A15: HK stated category total HKD | B15: 74800 | C15: Simplified relocation-model categories. | D15: finance/uk-move-financial-model.md §1
... A19: London monthly cash burn GBP | B19: 4550 | C19: Latest London cash burn, updated to remove the former £60/mo DB letting-agent allowance because agency fee is one-off. | D19: finance/uk-move-financial-model.md §9-11; user correction 2026-07-10
A20: London monthly net-worth burn GBP | B20: =B19-B21 | C20: London cash burn less DB principal/equity component. | D20: Derived from B19 and B21
A21: DB principal/equity component GBP | B21: 1369 | C21: Mortgage principal, cash outflow but equity accumulation. | D21: finance/uk-move-financial-model.md §11
A22: HK school fees Julian pays HKD | B22: 6905 | C22: Budget.md school-fee line, may differ from simplified 6,500. | D22: finance/budget.md
A23: HK school fee simplified HKD | B23: 6500 | C23: Relocation-model simplified tuition line. | D23: finance/uk-move-financial-model.md §1
A24: HK helper HKD | B24: 3000 | C24: Helper line in Bills. | D24: finance/budget.md
A25: Potential Clodagh contribution HKD | B25: 3050 | C25: Approx half of HK school fee, not currently paid. | D25: finance/uk-vs-hk-cost-comparison.md
A26: UK cleaner placeholder GBP | B26: 460 | C26: DISCRETIONARY during search (do own cleaning while unemployed). 8h/wk @ ~£14.50/hr settled. | D26: User current hypothesis
A27: UK Sophia activities placeholder GBP | B27: 480 | C27: London monthly budget Sophia line. | D27: finance/london-monthly-budget.md
A28: Moving one-off low GBP | B28: 10000 | C28: Transition one-offs low estimate. | D28: finance/uk-vs-hk-cost-comparison.md
A29: Moving one-off high GBP | B29: 25000 | C29: Transition one-offs high estimate. | D29: finance/uk-vs-hk-cost-comparison.md
A30: DB flat expected rent HKD | B30: 22000 | C30: Agent-estimated monthly rent for DB flat if UK-based. | D30: User correction 2026-07-10
A31: DB flat letting agency fee HKD one-off | B31: 11000 | C31: 50% of one month rent, one-off fee, not monthly central burn. | D31: User correction 2026-07-10
A32: DB flat mortgage total HKD | B32: 25827 | C32: Monthly DB mortgage payment. | D32: finance/uk-move-financial-model.md §11
... A44: UK car purchase GBP one-off | B44: 4000 | C44: One-off: ~8yr-old small petrol hatchback. Treated like moving one-offs, not monthly burn. | D44: Julian research 2026-07-10
A45: London CORRECTED cash burn GBP | B45: =B19+B26+B42+B43 | C45: London cash burn incl. realistic cleaner + babysitter + car. Supersedes B19 as the honest survival burn. | D45: Derived 2026-07-10
A46: London CORRECTED net-worth burn GBP | B46: =B45-B21 | C46: Corrected cash burn less DB principal/equity. | D46: Derived from B45 and B21
A47: London search-phase car GBP | B47: 0 | C47: Car deferred entirely during search: use TfL (already in base burn). | D47: Deferrable
A48: London search-phase babysitting GBP | B48: 30 | C48: Largely eliminated: home while searching; small residual for interviews/networking. | D48: Deferrable
A49: London search-phase cleaning GBP | B49: 50 | C49: Largely eliminated: do own cleaning while unemployed; occasional deep-clean only. | D49: Deferrable
A50: London SEARCH-PHASE lean cash burn GBP | B50: =B19+B47+B48+B49 | C50: Non-optional survival burn during job search: base + minimal help, no car. | D50: Derived 2026-07-10
A51: London SEARCH-PHASE net-worth burn GBP | B51: =B50-B21 | C51: Lean search cash burn less DB principal. | D51: Derived

Sheet Category Map
A1: Category-Aligned Cost Reconciliation
A2: Rows use the canonical money-tracker categories. The table exposes where HK actuals, HK budget, and UK forecast are not like-for-like.
A3: Category | B3: HK budget target HKD | C3: HK stated relocation HKD | D3: HK actual allocation HKD | E3: UK forecast GBP | F3: UK forecast HKD | G3: Delta UK vs HK actual GBP | H3: Treatment | I3: Confidence | J3: Notes
A4: Housing | B4: 32696 | C4: 29000 | D4: ='Housing Mechanics'!B31*Inputs!$B$4 | E4: ='Housing Mechanics'!B32 | F4: =E4*Inputs!$B$4 | G4: =E4-D4/Inputs!$B$4 | H4: Property mechanics normalized | I4: High | J4: Housing uses Housing Mechanics, not raw HK$29k vs UK row. One-off DB agency fee excluded from monthly central.
A5: Tax | B5: 24478 | C5: 0 | D5: 0 | E5: 0 | F5: =E5*Inputs!$B$4 | G5: =E5-D5/Inputs!$B$4 | H5: Income-tax handled in income scenarios | I5: High | J5: Budget tax provision relates prior Telstra year and should not be in living-cost floor.
A6: Travel | B6: 56000 | C6: 5000 | D6: 5000 | E6: 0 | F6: =E6*Inputs!$B$4 | G6: =E6-D6/Inputs!$B$4 | H6: Not in corrected UK burn | I6: Low | J6: UK corrected burn B45 does not include a separate holidays/travel line; review separately if a travel budget is required.
A7: Tuition | B7: 7706 | C7: 6500 | D7: 6500 | E7: 0 | F7: =E7*Inputs!$B$4 | G7: =E7-D7/Inputs!$B$4 | H7: Structural HK-only saving | I7: High | J7: UK state school removes school fees, but activities move elsewhere.
A8: Dining out | B8: 7089 | C8: 10000 | D8: 10000 | E8: 300 | F8: =E8*Inputs!$B$4 | G8: =E8-D8/Inputs!$B$4 | H8: Discretionary | I8: Medium | J8: Uses London budget dining/takeaway line. Search-phase keeps 40%.
A9: Groceries | B9: 6000 | C9: 9000 | D9: 9000 | E9: 620 | F9: =E9*Inputs!$B$4 | G9: =E9-D9/Inputs!$B$4 | H9: UK forecast lower | I9: Medium | J9: Uses London budget groceries line.
A10: Bills / household utilities | B10: 5956 | C10: 6000 | D10: =C10-Inputs!$B$24 | E10: 571 | F10: =E10*Inputs!$B$4 | G10: =E10-D10/Inputs!$B$4 | H10: Helper split out | I10: Medium | J10: HK stated Bills line was HK$6k including helper HK$3k. Helper is split to Domestic help / cleaner; this row is household utilities / bills only.
A11: Health / gym | B11: 905 | C11: 500 | D11: 500 | E11: 65 | F11: =E11*Inputs!$B$4 | G11: =E11-D11/Inputs!$B$4 | H11: Discretionary during search | I11: Medium | J11: UK gym/fitness line. Search-phase set to zero.
A12: Leisure | B12: 1670 | C12: 3000 | D12: 3000 | E12: 250 | F12: =E12*Inputs!$B$4 | G12: =E12-D12/Inputs!$B$4 | H12: Discretionary | I12: Medium | J12: London leisure/hobbies line. Search-phase keeps 30%.
A13: Medical | B13: 800 | C13: 1000 | D13: 1000 | E13: 0 | F13: =E13*Inputs!$B$4 | G13: =E13-D13/Inputs!$B$4 | H13: NHS saving | I13: Medium | J13: NHS saving; dental/prescriptions remain an omission risk.
A14: Transport (TfL) | B14: 1650 | C14: 3000 | D14: 3000 | E14: 220 | F14: =E14*Inputs!$B$4 | G14: =E14-D14/Inputs!$B$4 | H14: Non-optional | I14: Medium | J14: TfL / Oyster plus occasional rail. Car is now split below.
A15: Car | B15: 0 | C15: 0 | D15: 0 | E15: =Inputs!$B$43 | F15: =E15*Inputs!$B$4 | G15: =E15-D15/Inputs!$B$4 | H15: Discretionary during search | I15: Medium | J15: Settled-life car running cost. Search-phase car is Inputs B47, currently zero.
A16: Shopping / clothing | B16: 700 | C16: 0 | D16: 0 | E16: 70 | F16: =E16*Inputs!$B$4 | G16: =E16-D16/Inputs!$B$4 | H16: Discretionary | I16: Low | J16: UK clothing/shopping line. Search-phase keeps 40%.
A17: Beauty / personal care | B17: 825 | C17: 1000 | D17: 1000 | E17: 75 | F17: =E17*Inputs!$B$4 | G17: =E17-D17/Inputs!$B$4 | H17: Non-optional | I17: Medium | J17: Personal care line kept during search.
A18: Savings & Investments | B18: 0 | C18: 0 | D18: 0 | E18: 0 | F18: =E18*Inputs!$B$4 | G18: =E18-D18/Inputs!$B$4 | H18: Excluded from floor | I18: High | J18: No active saving assumed in survival-floor comparison.
A19: Financial / work subs | B19: 667 | C19: 800 | D19: 800 | E19: 38 | F19: =E19*Inputs!$B$4 | G19: =E19-D19/Inputs!$B$4 | H19: Non-optional | I19: Medium | J19: Claude + ChatGPT work AI subscriptions.
A20: Sophia essentials | B20: 0 | C20: 0 | D20: 0 | E20: =Inputs!$B$27*0.5 | F20: =E20*Inputs!$B$4 | G20: =E20-D20/Inputs!$B$4 | H20: Non-optional | I20: Low | J20: Provisional 50% split of the Sophia line until activities / essentials are itemised.
A21: Sophia clubs/activities | B21: 0 | C21: 0 | D21: 0 | E21: =Inputs!$B$27*0.5 | F21: =E21*Inputs!$B$4 | G21: =E21-D21/Inputs!$B$4 | H21: Discretionary during search | I21: Low | J21: Provisional 50% split of the Sophia line. Search-phase keeps half.
A22: Buffer / lumpy | B22: 0 | C22: 9140 | D22: 9140 | E22: 632 | F22: =E22*Inputs!$B$4 | G22: =E22-D22/Inputs!$B$4 | H22: Half during search | I22: Low | J22: Search-phase keeps 50% of the buffer/lumpy line.
A23: Domestic help / cleaner | B23: 0 | C23: 0 | D23: =Inputs!$B$24 | E23: =Inputs!$B$26 | F23: =E23*Inputs!$B$4 | G23: =E23-D23/Inputs!$B$4 | H23: Helper versus cleaner | I23: Low | J23: HK full-time helper cost is HK$3k/mo. UK cleaner uses settled-life input B26; search-phase cleaning uses B49.
A24: Babysitting / childcare cover | B24: 0 | C24: 0 | D24: 0 | E24: =Inputs!$B$42 | F24: =E24*Inputs!$B$4 | G24: =E24-D24/Inputs!$B$4 | H24: UK-only childcare replacement | I24: Low | J24: UK settled babysitting uses B42; search-phase babysitting uses B48.
A25: TOTAL | B25: =SUM(B4:B24) | C25: =SUM(C4:C24) | D25: =SUM(D4:D24) | E25: =SUM(E4:E24) | F25: =SUM(F4:F24) | G25: =SUM(G4:G24)

Sheet Scenario Summary
A1: Income Floor Scenario Summary
A2: Tests whether HK$100k/month is actually less viable than UK £120k/year once tax, rent offset, and cash vs net-worth burn are separated.
A3: Scenario | B3: Location | C3: Gross income HKD/mo | D3: Net salary HKD/mo | E3: Property income offset HKD/mo | F3: Cost basis HKD/mo | G3: Monthly surplus HKD | H3: Notes
A4: HK 100k role - trend actuals, no Cecil offset | B4: HK | C4: =Inputs!$B$5 | D4: =Inputs!$B$5*(1-Inputs!$B$6) | E4: 0 | F4: =Inputs!$B$14 | G4: =D4+E4-F4 | H4: Baseline suspect comparison
A5: HK 100k role - trend actuals, with Cecil offset | B5: HK | C5: =Inputs!$B$5 | D5: =Inputs!$B$5*(1-Inputs!$B$6) | E5: =Inputs!$B$18*Inputs!$B$4 | F5: =Inputs!$B$14 | G5: =D5+E5-F5 | H5: Likely correct HK cash view
A6: HK 100k role - mean actuals, with Cecil offset | B6: HK | C6: =Inputs!$B$5 | D6: =Inputs!$B$5*(1-Inputs!$B$6) | E6: =Inputs!$B$18*Inputs!$B$4 | F6: =Inputs!$B$13 | G6: =D6+E6-F6 | H6: More conservative actuals view
A7: HK 100k role - trend, Clodagh pays half school fee | B7: HK | C7: =Inputs!$B$5 | D7: =Inputs!$B$5*(1-Inputs!$B$6) | E7: =Inputs!$B$18*Inputs!$B$4 | F7: =Inputs!$B$14-Inputs!$B$25 | G7: =D7+E7-F7 | H7: Contingent, not base case
A8: HK 125k senior role - trend with Cecil offset | B8: HK | C8: =Inputs!$B$7 | D8: =Inputs!$B$7*(1-Inputs!$B$8) | E8: =Inputs!$B$18*Inputs!$B$4 | F8: =Inputs!$B$14 | G8: =D8+E8-F8 | H8: Senior HK recovery case
A9: UK floor role - London cash burn | B9: UK | C9: =Inputs!$B$11*Inputs!$B$4/12 | D9: =Inputs!$B$12*Inputs!$B$4/12 | E9: 0 | F9: =Inputs!$B$19*Inputs!$B$4 | G9: =D9+E9-F9 | H9: Cash-flow break-even floor
A10: UK £120k role - London cash burn | B10: UK | C10: =Inputs!$B$9*Inputs!$B$4/12 | D10: =Inputs!$B$10*Inputs!$B$4/12 | E10: 0 | F10: =Inputs!$B$19*Inputs!$B$4 | G10: =D10+E10-F10 | H10: Strong UK role
A11: UK £120k role - net-worth burn | B11: UK | C11: =Inputs!$B$9*Inputs!$B$4/12 | D11: =Inputs!$B$10*Inputs!$B$4/12 | E11: 0 | F11: =Inputs!$B$20*Inputs!$B$4 | G11: =D11+E11-F11 | H11: Cash burn less DB principal/equity
A12: HK 100k role - trend actuals, Cecil offset, net-worth basis | B12: HK | C12: =Inputs!$B$5 | D12: =Inputs!$B$5*(1-Inputs!$B$6) | E12: =Inputs!$B$18*Inputs!$B$4 | F12: =Inputs!$B$14-Inputs!$B$21*Inputs!$B$4 | G12: =D12+E12-F12 | H12: Adds back DB-flat principal (equity) to match UK net-worth row
A13: HK 100k role - mean actuals, Cecil offset, net-worth basis | B13: HK | C13: =Inputs!$B$5 | D13: =Inputs!$B$5*(1-Inputs!$B$6) | E13: =Inputs!$B$18*Inputs!$B$4 | F13: =Inputs!$B$13-Inputs!$B$21*Inputs!$B$4 | G13: =D13+E13-F13 | H13: Symmetric net-worth basis, conservative 12-mo denominator
A15: First-pass finding
A16: The suspicious statement is confirmed: | B16: HK$100k/month is not automatically unlivable once Cecil Road rent is offset.
A17: Base HK100k with trend actuals and Cecil offset: | B17: =G5
A18: Base HK100k with mean actuals and Cecil offset: | B18: =G6
A19: UK £120k with London cash burn: | B19: =G10
A20: Interpretation: | B20: On cash, HK$100k (trend actuals) is level-to-ahead of UK £120k once Cecil rent is offset - they are the SAME ~£120k gross. On a symmetric net-worth basis (DB-flat principal added back on both sides) HK is ahead. 'No cheap floor' is wrong; the real UK edge is a LOWER break-even gross (~£77.5k), not more surplus at equal pay.
A21: HK100k trend, net-worth basis (symmetric): | B21: =G12
A22: UK £120k, net-worth basis: | B22: =G11
A24: CORRECTED SCENARIOS (cleaner £460 + babysitter £215 + car £225/mo added to London burn)
A25: UK £120k role - CORRECTED London cash burn | B25: UK | C25: =Inputs!$B$9*Inputs!$B$4/12 | D25: =Inputs!$B$10*Inputs!$B$4/12 | E25: 0 | F25: =Inputs!$B$45*Inputs!$B$4 | G25: =D25+E25-F25 | H25: Strong UK role, honest burn
A26: UK £120k role - CORRECTED net-worth burn | B26: UK | C26: =Inputs!$B$9*Inputs!$B$4/12 | D26: =Inputs!$B$10*Inputs!$B$4/12 | E26: 0 | F26: =Inputs!$B$46*Inputs!$B$4 | G26: =D26+E26-F26 | H26: Strong UK role, honest net-worth burn
A27: UK £77.5k floor - CORRECTED London cash burn | B27: UK | C27: =Inputs!$B$11*Inputs!$B$4/12 | D27: =Inputs!$B$12*Inputs!$B$4/12 | E27: 0 | F27: =Inputs!$B$45*Inputs!$B$4 | G27: =D27+E27-F27 | H27: Does the old floor still cover the honest burn?

Sheet Audit Flags
A1: Audit Flags
A2: Items that must be resolved before the model can update the relocation verdict.
A3: Flag | B3: Severity | C3: Detail
A4: Cecil Road rent offset | B4: High | C4: HK stay scenarios must include the net UK rent. Without it HK looks too weak.
A5: Tax provision in budget.md | B5: High | C5: HK$24.5k/mo tax provision reflects prior/current tax context, not automatically the future HK100k role.
A6: Travel budget | B6: High | C6: Canonical budget shows HK$56k/mo provision while relocation model uses HK$5k/mo. Needs actual transaction breakdown.
A7: UK cleaner equivalent | B7: Medium | C7: HK helper HK$3k/mo may be replaced by UK part-time cleaner. Current London budget excludes this unless placeholder added.
A8: Sophia activities | B8: Medium | C8: HK school fees disappear, but UK activities/school extras need explicit category mapping.
A9: Actuals gap | B9: High | C9: HK actuals exceed simplified categories by HK$9-17k/mo. Need classify one-off versus recurring and UK-equivalent.
A10: Cash vs net worth | B10: High | C10: DB principal is cash outflow but equity. Keep both views.
A11: Clodagh contribution | B11: Medium | C11: Do not use as base case while defaulting, but model as contingent case.

Sheet Source Notes
A1: Source Notes
A2: Where the workbook inputs came from.
A3: Source | B3: Used for | C3: Path
A4: budget.md | B4: Canonical HK budget categories and category targets. | C4: wiki/finance/budget.md
A5: money-tracker.md | B5: 15 top-level category taxonomy. | C5: wiki/finance/money-tracker.md
A6: uk-move-financial-model.md | B6: HK actual burn, stated relocation categories, runway, DB flat mechanics. | C6: wiki/finance/uk-move-financial-model.md
A7: uk-vs-hk-cost-comparison.md | B7: Both-property Test A, Cecil Road rent offset, cost-comparison caveats. | C7: wiki/finance/uk-vs-hk-cost-comparison.md
A8: london-monthly-budget.md | B8: London living-cost line items. | C8: wiki/finance/london-monthly-budget.md
A9: uk-150k-feasibility-report.md | B9: UK floor salary and net-worth / cash-flow break-even distinction. | C9: wiki/career/uk-150k-feasibility-report.md
A10: uk-150k-feasibility-jh-clarifications-2026-07-09.md | B10: PAYE net estimates for UK salary points. | C10: wiki/career/uk-150k-feasibility-jh-clarifications-2026-07-09.md
A11: Housing Mechanics | B11: DB flat rent HK$22,000/mo and one-off agency fee HK$11,000 from Julian correction 2026-07-10; DB mortgage/fees from uk-move-financial-model §11; Cecil Road rent/tax from uk-vs-hk-cost-comparison §1.
A12: Helper / cleaner / babysitting split | B12: Babysitting / childcare cover added 2026-07-10 as explicit UK placeholder. HK helper is HK$3,000/mo and is split out from Bills; UK cleaner is Inputs B26; UK babysitting is Inputs B42.
A13: Mandatory / optional split | B13: Added Opt (UK, during search) and UK search-phase GBP/mo columns on 2026-07-10, mirroring budget.md Non-optional / Discretionary convention. Added explicit car row and B50 cross-check.
